setup.py
parseOneResumeSentence/__init__.py
parseOneResumeSentence.egg-info/PKG-INFO
parseOneResumeSentence.egg-info/SOURCES.txt
parseOneResumeSentence.egg-info/dependency_links.txt
parseOneResumeSentence.egg-info/not-zip-safe
parseOneResumeSentence.egg-info/top_level.txt