Metadata-Version: 1.0
Name: parseOneResumeSentence
Version: 0.0
Summary: Parses a sentence
Home-page: UNKNOWN
Author: pandro01
Author-email: rohitpandey576@gmail.com
License: None
Platform: UNKNOWN
